LICENSE.txt
README.rst
setup.py
keepalive/__init__.py
keepalive/keepalive.py
keepalive_socket.egg-info/PKG-INFO
keepalive_socket.egg-info/SOURCES.txt
keepalive_socket.egg-info/dependency_links.txt
keepalive_socket.egg-info/top_level.txt