Metadata-Version: 2.1
Name: keepalive-socket
Version: 0.0.1
Summary: TBA
Home-page: https://github.com/sfinktah/keepalive
Author: Christopher Anderson
Author-email: sfinktah@github.spamtrak.org
License: MIT
Platform: UNKNOWN
Classifier: Programming Language :: Python :: 3
Classifier: License :: OSI Approved :: MIT License
Classifier: Operating System :: OS Independent
Requires-Python: >=3.6
License-File: LICENSE.txt
